mle_runtime/__init__.py
mle_runtime/_mle_core.pyd
mle_runtime/cli.py
mle_runtime/core.py
mle_runtime/core_validation.py
mle_runtime/mle_runtime.py
mle_runtime/exporters/__init__.py
mle_runtime/exporters/pytorch_exporter.py
mle_runtime/exporters/sklearn_exporter.py
mle_runtime/exporters/tensorflow_exporter.py
mle_runtime/exporters/universal.py
mle_runtime/exporters/xgboost_exporter.py
mle_runtime-2.0.4.dist-info/licenses/LICENSE
mle_runtime-2.0.4.dist-info/METADATA
mle_runtime-2.0.4.dist-info/WHEEL
mle_runtime-2.0.4.dist-info/entry_points.txt
mle_runtime-2.0.4.dist-info/top_level.txt
mle_runtime-2.0.4.dist-info/RECORD
