Metadata-Version: 2.4
Name: mle-runtime
Version: 2.0.4
Summary: MLE Runtime - High-Performance Machine Learning Inference Engine
Home-page: https://github.com/vinaykamble289/mle-runtime
Author: Vinay Kamble
Author-email: Vinay Kamble <vinaykamble289@gmail.com>
Maintainer-email: Vinay Kamble <vinaykamble289@gmail.com>
License: MIT
Project-URL: Homepage, https://github.com/vinaykamble289/mle-runtime
Project-URL: Repository, https://github.com/vinaykamble289/mle-runtime
Project-URL: Documentation, https://github.com/vinaykamble289/mle-runtime#readme
Project-URL: Bug Reports, https://github.com/vinaykamble289/mle-runtime/issues
Project-URL: Changelog, https://github.com/vinaykamble289/mle-runtime/releases
Keywords: machine learning,inference,runtime,optimization,performance,scikit-learn,pytorch,xgboost,lightgbm,catboost,neural networks,deep learning,model deployment,production,c++,cuda,gpu acceleration
Classifier: Development Status :: 4 - Beta
Classifier: Intended Audience :: Developers
Classifier: Intended Audience :: Science/Research
Classifier: License :: OSI Approved :: MIT License
Classifier: Operating System :: OS Independent
Classifier: Programming Language :: Python :: 3
Classifier: Programming Language :: Python :: 3.8
Classifier: Programming Language :: Python :: 3.9
Classifier: Programming Language :: Python :: 3.10
Classifier: Programming Language :: Python :: 3.11
Classifier: Programming Language :: Python :: 3.12
Classifier: Programming Language :: C++
Classifier: Topic :: Scientific/Engineering :: Artificial Intelligence
Classifier: Topic :: Software Development :: Libraries :: Python Modules
Classifier: Topic :: System :: Hardware :: Symmetric Multi-processing
Requires-Python: >=3.8
License-File: LICENSE
Requires-Dist: numpy>=1.20.0
Requires-Dist: scipy>=1.7.0
Provides-Extra: dev
Requires-Dist: pytest>=6.0; extra == "dev"
Requires-Dist: pytest-benchmark>=3.4.0; extra == "dev"
Requires-Dist: black>=21.0.0; extra == "dev"
Requires-Dist: flake8>=3.9.0; extra == "dev"
Requires-Dist: mypy>=0.910; extra == "dev"
Provides-Extra: all
Requires-Dist: scikit-learn>=1.0.0; extra == "all"
Requires-Dist: torch>=1.9.0; extra == "all"
Requires-Dist: xgboost>=1.5.0; extra == "all"
Requires-Dist: lightgbm>=3.2.0; extra == "all"
Requires-Dist: catboost>=1.0.0; extra == "all"
Provides-Extra: gpu
Requires-Dist: cupy-cuda11x>=9.0.0; extra == "gpu"
Dynamic: author
Dynamic: home-page
Dynamic: license-file
Dynamic: requires-python
